farm_precip_project/__init__.py
farm_precip_project/analysis.py
farm_precip_project/eda_work.py
farm_precip_project/merge_csvs.py
farm_precip_project/scrape_farm.py
farm_precip_project/scrape_precip.py
farm_precip_project-0.1.3.dist-info/WHEEL
farm_precip_project-0.1.3.dist-info/METADATA
farm_precip_project-0.1.3.dist-info/RECORD
