Metadata-Version: 2.3
Name: farm_precip_project
Version: 0.1.3
Summary: Add your description here
License: MIT
Classifier: Programming Language :: Python :: 3
Classifier: Operating System :: OS Independent
Requires-Dist: bs4>=0.0.2
Requires-Dist: ipykernel>=7.1.0
Requires-Dist: jupyter>=1.1.1
Requires-Dist: matplotlib>=3.10.7
Requires-Dist: numpy>=2.3.5
Requires-Dist: openpyxl>=3.1.5
Requires-Dist: pandas>=2.3.3
Requires-Dist: requests>=2.32.5
Requires-Dist: seaborn>=0.13.2
Requires-Dist: streamlit>=1.52.1
Requires-Dist: tabulate>=0.9.0
Requires-Python: >=3.13
